[
    {
        "name": "Internal",
        "status": [
            {
                "name": "Cloverse (lvl 1)",
                "url": "https://ntfy.twint.my.id/",
                "method": "GET",
                "uptime": 100,
                "raw": [
                    {
                        "status": 200,
                        "date": 1767310797410
                    },
                    {
                        "status": 200,
                        "date": 1767316686903
                    },
                    {
                        "status": 200,
                        "date": 1767323641049
                    },
                    {
                        "status": 200,
                        "date": 1767327890563
                    },
                    {
                        "status": 200,
                        "date": 1767329837162
                    },
                    {
                        "status": 200,
                        "date": 1767331565856
                    },
                    {
                        "status": 200,
                        "date": 1767332896676
                    },
                    {
                        "status": 200,
                        "date": 1767335184870
                    },
                    {
                        "status": 200,
                        "date": 1767336952653
                    },
                    {
                        "status": 200,
                        "date": 1767338491489
                    },
                    {
                        "status": 200,
                        "date": 1767339762434
                    },
                    {
                        "status": 200,
                        "date": 1767342189629
                    },
                    {
                        "status": 200,
                        "date": 1767343851430
                    },
                    {
                        "status": 200,
                        "date": 1767345610669
                    },
                    {
                        "status": 200,
                        "date": 1767347075235
                    },
                    {
                        "status": 200,
                        "date": 1767349011725
                    },
                    {
                        "status": 200,
                        "date": 1767350632605
                    },
                    {
                        "status": 200,
                        "date": 1767352491531
                    },
                    {
                        "status": 200,
                        "date": 1767353877526
                    },
                    {
                        "status": 200,
                        "date": 1767357126073
                    },
                    {
                        "status": 200,
                        "date": 1767360566976
                    },
                    {
                        "status": 200,
                        "date": 1767361831830
                    },
                    {
                        "status": 200,
                        "date": 1767363387059
                    },
                    {
                        "status": 200,
                        "date": 1767365048574
                    },
                    {
                        "status": 200,
                        "date": 1767367034668
                    },
                    {
                        "status": 200,
                        "date": 1767368526248
                    },
                    {
                        "status": 200,
                        "date": 1767370781829
                    },
                    {
                        "status": 200,
                        "date": 1767372493680
                    },
                    {
                        "status": 200,
                        "date": 1767374074853
                    },
                    {
                        "status": 200,
                        "date": 1767375625790
                    },
                    {
                        "status": 200,
                        "date": 1767378195331
                    },
                    {
                        "status": 200,
                        "date": 1767379832403
                    },
                    {
                        "status": 200,
                        "date": 1767381084986
                    },
                    {
                        "status": 200,
                        "date": 1767382592687
                    },
                    {
                        "status": 200,
                        "date": 1767385069262
                    },
                    {
                        "status": 200,
                        "date": 1767386545538
                    },
                    {
                        "status": 200,
                        "date": 1767388354367
                    },
                    {
                        "status": 200,
                        "date": 1767389819576
                    },
                    {
                        "status": 200,
                        "date": 1767392171441
                    },
                    {
                        "status": 200,
                        "date": 1767393796685
                    },
                    {
                        "status": 200,
                        "date": 1767395701516
                    },
                    {
                        "status": 200,
                        "date": 1767397095516
                    },
                    {
                        "status": 200,
                        "date": 1767402793345
                    },
                    {
                        "status": 200,
                        "date": 1767409510112
                    },
                    {
                        "status": 200,
                        "date": 1767413141507
                    },
                    {
                        "status": 200,
                        "date": 1767415844980
                    },
                    {
                        "status": 200,
                        "date": 1767417435769
                    },
                    {
                        "status": 200,
                        "date": 1767419033275
                    },
                    {
                        "status": 200,
                        "date": 1767421475649
                    },
                    {
                        "status": 200,
                        "date": 1767423131086
                    }
                ]
            },
            {
                "name": "Cloverse (lvl 2)",
                "url": "https://git.serversmp.xyz/",
                "method": "GET",
                "uptime": 100,
                "raw": [
                    {
                        "status": 200,
                        "date": 1767310797853
                    },
                    {
                        "status": 200,
                        "date": 1767316687154
                    },
                    {
                        "status": 200,
                        "date": 1767323641400
                    },
                    {
                        "status": 200,
                        "date": 1767327890863
                    },
                    {
                        "status": 200,
                        "date": 1767329838407
                    },
                    {
                        "status": 200,
                        "date": 1767331566051
                    },
                    {
                        "status": 200,
                        "date": 1767332897121
                    },
                    {
                        "status": 200,
                        "date": 1767335185366
                    },
                    {
                        "status": 200,
                        "date": 1767336952871
                    },
                    {
                        "status": 200,
                        "date": 1767338491814
                    },
                    {
                        "status": 200,
                        "date": 1767339762854
                    },
                    {
                        "status": 200,
                        "date": 1767342189881
                    },
                    {
                        "status": 200,
                        "date": 1767343851652
                    },
                    {
                        "status": 200,
                        "date": 1767345610942
                    },
                    {
                        "status": 200,
                        "date": 1767347075631
                    },
                    {
                        "status": 200,
                        "date": 1767349012857
                    },
                    {
                        "status": 200,
                        "date": 1767350633186
                    },
                    {
                        "status": 200,
                        "date": 1767352491707
                    },
                    {
                        "status": 200,
                        "date": 1767353877694
                    },
                    {
                        "status": 200,
                        "date": 1767357126444
                    },
                    {
                        "status": 200,
                        "date": 1767360567190
                    },
                    {
                        "status": 200,
                        "date": 1767361832071
                    },
                    {
                        "status": 200,
                        "date": 1767363387260
                    },
                    {
                        "status": 200,
                        "date": 1767365049340
                    },
                    {
                        "status": 200,
                        "date": 1767367034910
                    },
                    {
                        "status": 200,
                        "date": 1767368526469
                    },
                    {
                        "status": 200,
                        "date": 1767370782164
                    },
                    {
                        "status": 200,
                        "date": 1767372494066
                    },
                    {
                        "status": 200,
                        "date": 1767374075305
                    },
                    {
                        "status": 200,
                        "date": 1767375626118
                    },
                    {
                        "status": 200,
                        "date": 1767378195758
                    },
                    {
                        "status": 200,
                        "date": 1767379832667
                    },
                    {
                        "status": 200,
                        "date": 1767381085254
                    },
                    {
                        "status": 200,
                        "date": 1767382593106
                    },
                    {
                        "status": 200,
                        "date": 1767385069670
                    },
                    {
                        "status": 200,
                        "date": 1767386545901
                    },
                    {
                        "status": 200,
                        "date": 1767388354551
                    },
                    {
                        "status": 200,
                        "date": 1767389819784
                    },
                    {
                        "status": 200,
                        "date": 1767392171637
                    },
                    {
                        "status": 200,
                        "date": 1767393797666
                    },
                    {
                        "status": 200,
                        "date": 1767395701812
                    },
                    {
                        "status": 200,
                        "date": 1767397095723
                    },
                    {
                        "status": 200,
                        "date": 1767402793776
                    },
                    {
                        "status": 200,
                        "date": 1767409510618
                    },
                    {
                        "status": 200,
                        "date": 1767413142174
                    },
                    {
                        "status": 200,
                        "date": 1767415845466
                    },
                    {
                        "status": 200,
                        "date": 1767417436019
                    },
                    {
                        "status": 200,
                        "date": 1767419033547
                    },
                    {
                        "status": 200,
                        "date": 1767421476040
                    },
                    {
                        "status": 200,
                        "date": 1767423131553
                    }
                ]
            },
            {
                "name": "Cloverse (lvl 3)",
                "url": "https://api.serversmp.xyz/",
                "method": "GET",
                "uptime": 100,
                "raw": [
                    {
                        "status": 200,
                        "date": 1767310799174
                    },
                    {
                        "status": 200,
                        "date": 1767316687377
                    },
                    {
                        "status": 200,
                        "date": 1767323641763
                    },
                    {
                        "status": 200,
                        "date": 1767327891328
                    },
                    {
                        "status": 200,
                        "date": 1767329839615
                    },
                    {
                        "status": 200,
                        "date": 1767331566241
                    },
                    {
                        "status": 200,
                        "date": 1767332897890
                    },
                    {
                        "status": 200,
                        "date": 1767335185807
                    },
                    {
                        "status": 200,
                        "date": 1767336953122
                    },
                    {
                        "status": 200,
                        "date": 1767338492096
                    },
                    {
                        "status": 200,
                        "date": 1767339763338
                    },
                    {
                        "status": 200,
                        "date": 1767342190112
                    },
                    {
                        "status": 200,
                        "date": 1767343851878
                    },
                    {
                        "status": 200,
                        "date": 1767345611591
                    },
                    {
                        "status": 200,
                        "date": 1767347076068
                    },
                    {
                        "status": 200,
                        "date": 1767349013232
                    },
                    {
                        "status": 200,
                        "date": 1767350633400
                    },
                    {
                        "status": 200,
                        "date": 1767352491864
                    },
                    {
                        "status": 200,
                        "date": 1767353877942
                    },
                    {
                        "status": 200,
                        "date": 1767357126855
                    },
                    {
                        "status": 200,
                        "date": 1767360567357
                    },
                    {
                        "status": 200,
                        "date": 1767361832375
                    },
                    {
                        "status": 200,
                        "date": 1767363387448
                    },
                    {
                        "status": 200,
                        "date": 1767365049727
                    },
                    {
                        "status": 200,
                        "date": 1767367035142
                    },
                    {
                        "status": 200,
                        "date": 1767368526642
                    },
                    {
                        "status": 200,
                        "date": 1767370782541
                    },
                    {
                        "status": 200,
                        "date": 1767372494426
                    },
                    {
                        "status": 200,
                        "date": 1767374075672
                    },
                    {
                        "status": 200,
                        "date": 1767375626882
                    },
                    {
                        "status": 200,
                        "date": 1767378196436
                    },
                    {
                        "status": 200,
                        "date": 1767379832889
                    },
                    {
                        "status": 200,
                        "date": 1767381085474
                    },
                    {
                        "status": 200,
                        "date": 1767382593501
                    },
                    {
                        "status": 200,
                        "date": 1767385070072
                    },
                    {
                        "status": 200,
                        "date": 1767386546531
                    },
                    {
                        "status": 200,
                        "date": 1767388355696
                    },
                    {
                        "status": 200,
                        "date": 1767389820140
                    },
                    {
                        "status": 200,
                        "date": 1767392171884
                    },
                    {
                        "status": 200,
                        "date": 1767393797876
                    },
                    {
                        "status": 200,
                        "date": 1767395702117
                    },
                    {
                        "status": 200,
                        "date": 1767397096131
                    },
                    {
                        "status": 200,
                        "date": 1767402794128
                    },
                    {
                        "status": 200,
                        "date": 1767409510931
                    },
                    {
                        "status": 200,
                        "date": 1767413142495
                    },
                    {
                        "status": 200,
                        "date": 1767415845916
                    },
                    {
                        "status": 200,
                        "date": 1767417436430
                    },
                    {
                        "status": 200,
                        "date": 1767419033798
                    },
                    {
                        "status": 200,
                        "date": 1767421476470
                    },
                    {
                        "status": 200,
                        "date": 1767423131966
                    }
                ]
            },
            {
                "name": "Cloverse (lvl 4)",
                "url": "https://chat.serversmp.xyz/",
                "method": "GET",
                "uptime": 100,
                "raw": [
                    {
                        "status": 200,
                        "date": 1767310799488
                    },
                    {
                        "status": 200,
                        "date": 1767316687563
                    },
                    {
                        "status": 200,
                        "date": 1767323642095
                    },
                    {
                        "status": 200,
                        "date": 1767327891627
                    },
                    {
                        "status": 200,
                        "date": 1767329839832
                    },
                    {
                        "status": 200,
                        "date": 1767331566390
                    },
                    {
                        "status": 200,
                        "date": 1767332898336
                    },
                    {
                        "status": 200,
                        "date": 1767335186624
                    },
                    {
                        "status": 200,
                        "date": 1767336953415
                    },
                    {
                        "status": 200,
                        "date": 1767338492367
                    },
                    {
                        "status": 200,
                        "date": 1767339763767
                    },
                    {
                        "status": 200,
                        "date": 1767342190358
                    },
                    {
                        "status": 200,
                        "date": 1767343852071
                    },
                    {
                        "status": 200,
                        "date": 1767345611855
                    },
                    {
                        "status": 200,
                        "date": 1767347076463
                    },
                    {
                        "status": 200,
                        "date": 1767349013736
                    },
                    {
                        "status": 200,
                        "date": 1767350633600
                    },
                    {
                        "status": 200,
                        "date": 1767352492165
                    },
                    {
                        "status": 200,
                        "date": 1767353878171
                    },
                    {
                        "status": 200,
                        "date": 1767357127157
                    },
                    {
                        "status": 200,
                        "date": 1767360567578
                    },
                    {
                        "status": 200,
                        "date": 1767361832584
                    },
                    {
                        "status": 200,
                        "date": 1767363387663
                    },
                    {
                        "status": 200,
                        "date": 1767365050073
                    },
                    {
                        "status": 200,
                        "date": 1767367035581
                    },
                    {
                        "status": 200,
                        "date": 1767368526803
                    },
                    {
                        "status": 200,
                        "date": 1767370782921
                    },
                    {
                        "status": 200,
                        "date": 1767372494836
                    },
                    {
                        "status": 200,
                        "date": 1767374076110
                    },
                    {
                        "status": 200,
                        "date": 1767375627208
                    },
                    {
                        "status": 200,
                        "date": 1767378196823
                    },
                    {
                        "status": 200,
                        "date": 1767379833169
                    },
                    {
                        "status": 200,
                        "date": 1767381085744
                    },
                    {
                        "status": 200,
                        "date": 1767382593923
                    },
                    {
                        "status": 200,
                        "date": 1767385070490
                    },
                    {
                        "status": 200,
                        "date": 1767386546847
                    },
                    {
                        "status": 200,
                        "date": 1767388355880
                    },
                    {
                        "status": 200,
                        "date": 1767389820336
                    },
                    {
                        "status": 200,
                        "date": 1767392172086
                    },
                    {
                        "status": 200,
                        "date": 1767393798060
                    },
                    {
                        "status": 200,
                        "date": 1767395702391
                    },
                    {
                        "status": 200,
                        "date": 1767397096377
                    },
                    {
                        "status": 200,
                        "date": 1767402794488
                    },
                    {
                        "status": 200,
                        "date": 1767409511251
                    },
                    {
                        "status": 200,
                        "date": 1767413142811
                    },
                    {
                        "status": 200,
                        "date": 1767415846324
                    },
                    {
                        "status": 200,
                        "date": 1767417436696
                    },
                    {
                        "status": 200,
                        "date": 1767419034032
                    },
                    {
                        "status": 200,
                        "date": 1767421476805
                    },
                    {
                        "status": 200,
                        "date": 1767423132542
                    }
                ]
            },
            {
                "name": "Clovara",
                "url": "https://pangolin.twint.my.id/",
                "method": "GET",
                "uptime": 100,
                "raw": [
                    {
                        "status": 200,
                        "date": 1767310800275
                    },
                    {
                        "status": 200,
                        "date": 1767316688072
                    },
                    {
                        "status": 200,
                        "date": 1767323642944
                    },
                    {
                        "status": 200,
                        "date": 1767327892169
                    },
                    {
                        "status": 200,
                        "date": 1767329840415
                    },
                    {
                        "status": 200,
                        "date": 1767331566845
                    },
                    {
                        "status": 200,
                        "date": 1767332898803
                    },
                    {
                        "status": 200,
                        "date": 1767335187635
                    },
                    {
                        "status": 200,
                        "date": 1767336953994
                    },
                    {
                        "status": 200,
                        "date": 1767338493223
                    },
                    {
                        "status": 200,
                        "date": 1767339764539
                    },
                    {
                        "status": 200,
                        "date": 1767342190855
                    },
                    {
                        "status": 200,
                        "date": 1767343852573
                    },
                    {
                        "status": 200,
                        "date": 1767345612369
                    },
                    {
                        "status": 200,
                        "date": 1767347077312
                    },
                    {
                        "status": 200,
                        "date": 1767349014879
                    },
                    {
                        "status": 200,
                        "date": 1767350634070
                    },
                    {
                        "status": 200,
                        "date": 1767352492735
                    },
                    {
                        "status": 200,
                        "date": 1767353878821
                    },
                    {
                        "status": 200,
                        "date": 1767357128044
                    },
                    {
                        "status": 200,
                        "date": 1767360568008
                    },
                    {
                        "status": 200,
                        "date": 1767361833220
                    },
                    {
                        "status": 200,
                        "date": 1767363388150
                    },
                    {
                        "status": 200,
                        "date": 1767365050986
                    },
                    {
                        "status": 200,
                        "date": 1767367035964
                    },
                    {
                        "status": 200,
                        "date": 1767368530825
                    },
                    {
                        "status": 200,
                        "date": 1767370783654
                    },
                    {
                        "status": 200,
                        "date": 1767372495499
                    },
                    {
                        "status": 200,
                        "date": 1767374076887
                    },
                    {
                        "status": 200,
                        "date": 1767375627946
                    },
                    {
                        "status": 200,
                        "date": 1767378206583
                    },
                    {
                        "status": 200,
                        "date": 1767379833672
                    },
                    {
                        "status": 200,
                        "date": 1767381086334
                    },
                    {
                        "status": 200,
                        "date": 1767382594531
                    },
                    {
                        "status": 200,
                        "date": 1767385071251
                    },
                    {
                        "status": 200,
                        "date": 1767386547547
                    },
                    {
                        "status": 200,
                        "date": 1767388356502
                    },
                    {
                        "status": 200,
                        "date": 1767389820810
                    },
                    {
                        "status": 200,
                        "date": 1767392172588
                    },
                    {
                        "status": 200,
                        "date": 1767393798850
                    },
                    {
                        "status": 200,
                        "date": 1767395703316
                    },
                    {
                        "status": 200,
                        "date": 1767397096788
                    },
                    {
                        "status": 200,
                        "date": 1767402795313
                    },
                    {
                        "status": 200,
                        "date": 1767409512024
                    },
                    {
                        "status": 200,
                        "date": 1767413146528
                    },
                    {
                        "status": 200,
                        "date": 1767415847223
                    },
                    {
                        "status": 200,
                        "date": 1767417437115
                    },
                    {
                        "status": 200,
                        "date": 1767419034468
                    },
                    {
                        "status": 200,
                        "date": 1767421477436
                    },
                    {
                        "status": 200,
                        "date": 1767423133364
                    }
                ]
            }
        ]
    },
    {
        "name": "External",
        "status": [
            {
                "name": "Cloudflare",
                "url": "https://search.twint.my.id/",
                "method": "GET",
                "uptime": 100,
                "raw": [
                    {
                        "status": 200,
                        "date": 1767310800319
                    },
                    {
                        "status": 200,
                        "date": 1767316688265
                    },
                    {
                        "status": 200,
                        "date": 1767323643375
                    },
                    {
                        "status": 200,
                        "date": 1767327892574
                    },
                    {
                        "status": 200,
                        "date": 1767329840627
                    },
                    {
                        "status": 200,
                        "date": 1767331567155
                    },
                    {
                        "status": 200,
                        "date": 1767332899146
                    },
                    {
                        "status": 200,
                        "date": 1767335187907
                    },
                    {
                        "status": 200,
                        "date": 1767336954070
                    },
                    {
                        "status": 200,
                        "date": 1767338493379
                    },
                    {
                        "status": 200,
                        "date": 1767339764771
                    },
                    {
                        "status": 200,
                        "date": 1767342190918
                    },
                    {
                        "status": 200,
                        "date": 1767343852888
                    },
                    {
                        "status": 200,
                        "date": 1767345612569
                    },
                    {
                        "status": 200,
                        "date": 1767347077525
                    },
                    {
                        "status": 200,
                        "date": 1767349015058
                    },
                    {
                        "status": 200,
                        "date": 1767350634272
                    },
                    {
                        "status": 200,
                        "date": 1767352492913
                    },
                    {
                        "status": 200,
                        "date": 1767353878940
                    },
                    {
                        "status": 200,
                        "date": 1767357128079
                    },
                    {
                        "status": 200,
                        "date": 1767360568058
                    },
                    {
                        "status": 200,
                        "date": 1767361833428
                    },
                    {
                        "status": 200,
                        "date": 1767363388225
                    },
                    {
                        "status": 200,
                        "date": 1767365051238
                    },
                    {
                        "status": 200,
                        "date": 1767367036324
                    },
                    {
                        "status": 200,
                        "date": 1767368531161
                    },
                    {
                        "status": 200,
                        "date": 1767370783819
                    },
                    {
                        "status": 200,
                        "date": 1767372495535
                    },
                    {
                        "status": 200,
                        "date": 1767374077043
                    },
                    {
                        "status": 200,
                        "date": 1767375628112
                    },
                    {
                        "status": 200,
                        "date": 1767378206842
                    },
                    {
                        "status": 200,
                        "date": 1767379833991
                    },
                    {
                        "status": 200,
                        "date": 1767381086421
                    },
                    {
                        "status": 200,
                        "date": 1767382594697
                    },
                    {
                        "status": 200,
                        "date": 1767385071463
                    },
                    {
                        "status": 200,
                        "date": 1767386547720
                    },
                    {
                        "status": 200,
                        "date": 1767388356818
                    },
                    {
                        "status": 200,
                        "date": 1767389821206
                    },
                    {
                        "status": 200,
                        "date": 1767392172656
                    },
                    {
                        "status": 200,
                        "date": 1767393798933
                    },
                    {
                        "status": 200,
                        "date": 1767395703681
                    },
                    {
                        "status": 200,
                        "date": 1767397097134
                    },
                    {
                        "status": 200,
                        "date": 1767402795439
                    },
                    {
                        "status": 200,
                        "date": 1767409512417
                    },
                    {
                        "status": 200,
                        "date": 1767413146872
                    },
                    {
                        "status": 200,
                        "date": 1767415847529
                    },
                    {
                        "status": 200,
                        "date": 1767417437205
                    },
                    {
                        "status": 200,
                        "date": 1767419034776
                    },
                    {
                        "status": 200,
                        "date": 1767421477744
                    },
                    {
                        "status": 200,
                        "date": 1767423133573
                    }
                ]
            },
            {
                "name": "Heroku",
                "url": "https://4get.twint.my.id/",
                "method": "GET",
                "uptime": 100,
                "raw": [
                    {
                        "status": 200,
                        "date": 1767310800651
                    },
                    {
                        "status": 200,
                        "date": 1767316688362
                    },
                    {
                        "status": 200,
                        "date": 1767323643625
                    },
                    {
                        "status": 200,
                        "date": 1767327893004
                    },
                    {
                        "status": 200,
                        "date": 1767329840743
                    },
                    {
                        "status": 200,
                        "date": 1767331567352
                    },
                    {
                        "status": 200,
                        "date": 1767332899395
                    },
                    {
                        "status": 200,
                        "date": 1767335188353
                    },
                    {
                        "status": 200,
                        "date": 1767336954280
                    },
                    {
                        "status": 200,
                        "date": 1767338493800
                    },
                    {
                        "status": 200,
                        "date": 1767339765157
                    },
                    {
                        "status": 200,
                        "date": 1767342191134
                    },
                    {
                        "status": 200,
                        "date": 1767343853107
                    },
                    {
                        "status": 200,
                        "date": 1767345612955
                    },
                    {
                        "status": 200,
                        "date": 1767347078003
                    },
                    {
                        "status": 200,
                        "date": 1767349015302
                    },
                    {
                        "status": 200,
                        "date": 1767350634967
                    },
                    {
                        "status": 200,
                        "date": 1767352493097
                    },
                    {
                        "status": 200,
                        "date": 1767353879021
                    },
                    {
                        "status": 200,
                        "date": 1767357128446
                    },
                    {
                        "status": 200,
                        "date": 1767360568157
                    },
                    {
                        "status": 200,
                        "date": 1767361833626
                    },
                    {
                        "status": 200,
                        "date": 1767363388563
                    },
                    {
                        "status": 200,
                        "date": 1767365051618
                    },
                    {
                        "status": 200,
                        "date": 1767367036402
                    },
                    {
                        "status": 200,
                        "date": 1767368531499
                    },
                    {
                        "status": 200,
                        "date": 1767370784198
                    },
                    {
                        "status": 200,
                        "date": 1767372495786
                    },
                    {
                        "status": 200,
                        "date": 1767374077470
                    },
                    {
                        "status": 200,
                        "date": 1767375628491
                    },
                    {
                        "status": 200,
                        "date": 1767378207215
                    },
                    {
                        "status": 200,
                        "date": 1767379834369
                    },
                    {
                        "status": 200,
                        "date": 1767381086539
                    },
                    {
                        "status": 200,
                        "date": 1767382595070
                    },
                    {
                        "status": 200,
                        "date": 1767385071973
                    },
                    {
                        "status": 200,
                        "date": 1767386547974
                    },
                    {
                        "status": 200,
                        "date": 1767388356948
                    },
                    {
                        "status": 200,
                        "date": 1767389821425
                    },
                    {
                        "status": 200,
                        "date": 1767392172740
                    },
                    {
                        "status": 200,
                        "date": 1767393799125
                    },
                    {
                        "status": 200,
                        "date": 1767395703773
                    },
                    {
                        "status": 200,
                        "date": 1767397097228
                    },
                    {
                        "status": 200,
                        "date": 1767402795876
                    },
                    {
                        "status": 200,
                        "date": 1767409512667
                    },
                    {
                        "status": 200,
                        "date": 1767413147071
                    },
                    {
                        "status": 200,
                        "date": 1767415847842
                    },
                    {
                        "status": 200,
                        "date": 1767417437357
                    },
                    {
                        "status": 200,
                        "date": 1767419034923
                    },
                    {
                        "status": 200,
                        "date": 1767421478068
                    },
                    {
                        "status": 200,
                        "date": 1767423134122
                    }
                ]
            },
            {
                "name": "Github",
                "url": "https://twint.my.id/",
                "method": "GET",
                "uptime": 100,
                "raw": [
                    {
                        "status": 200,
                        "date": 1767310800997
                    },
                    {
                        "status": 200,
                        "date": 1767316688450
                    },
                    {
                        "status": 200,
                        "date": 1767323643958
                    },
                    {
                        "status": 200,
                        "date": 1767327893196
                    },
                    {
                        "status": 200,
                        "date": 1767329840864
                    },
                    {
                        "status": 200,
                        "date": 1767331567438
                    },
                    {
                        "status": 200,
                        "date": 1767332899823
                    },
                    {
                        "status": 200,
                        "date": 1767335188666
                    },
                    {
                        "status": 200,
                        "date": 1767336954523
                    },
                    {
                        "status": 200,
                        "date": 1767338493998
                    },
                    {
                        "status": 200,
                        "date": 1767339765490
                    },
                    {
                        "status": 200,
                        "date": 1767342191365
                    },
                    {
                        "status": 200,
                        "date": 1767343853306
                    },
                    {
                        "status": 200,
                        "date": 1767345614191
                    },
                    {
                        "status": 200,
                        "date": 1767347078254
                    },
                    {
                        "status": 200,
                        "date": 1767349015580
                    },
                    {
                        "status": 200,
                        "date": 1767350635075
                    },
                    {
                        "status": 200,
                        "date": 1767352493184
                    },
                    {
                        "status": 200,
                        "date": 1767353879359
                    },
                    {
                        "status": 200,
                        "date": 1767357128723
                    },
                    {
                        "status": 200,
                        "date": 1767360568260
                    },
                    {
                        "status": 200,
                        "date": 1767361833728
                    },
                    {
                        "status": 200,
                        "date": 1767363388771
                    },
                    {
                        "status": 200,
                        "date": 1767365051936
                    },
                    {
                        "status": 200,
                        "date": 1767367036506
                    },
                    {
                        "status": 200,
                        "date": 1767368531590
                    },
                    {
                        "status": 200,
                        "date": 1767370784359
                    },
                    {
                        "status": 200,
                        "date": 1767372496106
                    },
                    {
                        "status": 200,
                        "date": 1767374077809
                    },
                    {
                        "status": 200,
                        "date": 1767375628645
                    },
                    {
                        "status": 200,
                        "date": 1767378207534
                    },
                    {
                        "status": 200,
                        "date": 1767379834627
                    },
                    {
                        "status": 200,
                        "date": 1767381086772
                    },
                    {
                        "status": 200,
                        "date": 1767382595402
                    },
                    {
                        "status": 200,
                        "date": 1767385072305
                    },
                    {
                        "status": 200,
                        "date": 1767386548229
                    },
                    {
                        "status": 200,
                        "date": 1767388357049
                    },
                    {
                        "status": 200,
                        "date": 1767389821535
                    },
                    {
                        "status": 200,
                        "date": 1767392172852
                    },
                    {
                        "status": 200,
                        "date": 1767393799316
                    },
                    {
                        "status": 200,
                        "date": 1767395704142
                    },
                    {
                        "status": 200,
                        "date": 1767397097321
                    },
                    {
                        "status": 200,
                        "date": 1767402796098
                    },
                    {
                        "status": 200,
                        "date": 1767409513015
                    },
                    {
                        "status": 200,
                        "date": 1767413147352
                    },
                    {
                        "status": 200,
                        "date": 1767415848027
                    },
                    {
                        "status": 200,
                        "date": 1767417437691
                    },
                    {
                        "status": 200,
                        "date": 1767419035050
                    },
                    {
                        "status": 200,
                        "date": 1767421478353
                    },
                    {
                        "status": 200,
                        "date": 1767423134379
                    }
                ]
            }
        ]
    }
]